{
  "format_version": "1.20.70",
  "minecraft:block": {
    "description": {
      "identifier": "fluffyalien_asn:import_bus",
      "menu_category": {
        "category": "items"
      },
      "traits": {
        "minecraft:placement_direction": {
          "enabled_states": ["minecraft:cardinal_direction"]
        }
      },
      "states": {
        "fluffyalien_asn:east": [false, true],
        "fluffyalien_asn:south": [false, true],
        "fluffyalien_asn:west": [false, true],
        "fluffyalien_asn:up": [false, true],
        "fluffyalien_asn:down": [false, true]
      }
    },
    "components": {
      "minecraft:custom_components": ["fluffyalien_asn:import_bus"],
      "tag:fluffyalien_asn:storage_cable_connectable": {},

      "minecraft:geometry": {
        "identifier": "geometry.fluffyalien_asn.storage_bus",
        "bone_visibility": {
          "south": "q.block_state('fluffyalien_asn:south')",
          "east": "q.block_state('fluffyalien_asn:east')",
          "west": "q.block_state('fluffyalien_asn:west')",
          "up": "q.block_state('fluffyalien_asn:up')",
          "down": "q.block_state('fluffyalien_asn:down')"
        }
      },
      "minecraft:material_instances": {
        "*": {
          "texture": "fluffyalien_asn:import_bus"
        }
      },
      "minecraft:collision_box": {
        "origin": [-4, 4, -8],
        "size": [8, 8, 12]
      },
      "minecraft:selection_box": {
        "origin": [-3, 5, -8],
        "size": [6, 6, 11]
      },
      "minecraft:light_dampening": 0,
      "minecraft:destructible_by_explosion": false,
      "minecraft:destructible_by_mining": {
        "seconds_to_destroy": 1
      },
      "minecraft:tick": {
        "interval_range": [5, 5]
      }
    },
    "permutations": [
      {
        "condition": "q.block_state('minecraft:cardinal_direction') == 'north'",
        "components": {
          "minecraft:transformation": {
            "rotation": [0, 0, 0]
          }
        }
      },
      {
        "condition": "q.block_state('minecraft:cardinal_direction') == 'south'",
        "components": {
          "minecraft:transformation": {
            "rotation": [0, 180, 0]
          }
        }
      },
      {
        "condition": "q.block_state('minecraft:cardinal_direction') == 'west'",
        "components": {
          "minecraft:transformation": {
            "rotation": [0, 90, 0]
          }
        }
      },
      {
        "condition": "q.block_state('minecraft:cardinal_direction') == 'east'",
        "components": {
          "minecraft:transformation": {
            "rotation": [0, -90, 0]
          }
        }
      }
    ]
  }
}
